{
  "id": "vibe-flag/009",
  "index": 9,
  "componentName": "VibeFlag009",
  "emoji": "🏴",
  "pack": "vibe_flag",
  "packTitle": "VIBE flag",
  "sourceUrl": "https://t.me/addstickers/vibe_flag",
  "width": 192,
  "height": 192,
  "kind": "animated",
  "mediaType": "video/webm",
  "sourceFormat": "video",
  "assetPath": "vibe-flag/009.9ce187a408a0.webm",
  "src": "/stickers/vibe-flag/009.9ce187a408a0.webm",
  "fps": 25,
  "frameCount": 74,
  "duration": 2.96,
  "sha256": "9ce187a408a0fea70c9c4492d54e126e1959b996784fc04b47802bcc85f1e30a",
  "firstFrameAssetPath": "vibe-flag/009.first-frame.e4816ca7a003.webp",
  "firstFrameSrc": "/stickers/vibe-flag/009.first-frame.e4816ca7a003.webp"
}
