{
  "id": "vibe-flag/017",
  "index": 17,
  "componentName": "VibeFlag017",
  "emoji": "🏴",
  "pack": "vibe_flag",
  "packTitle": "VIBE flag",
  "sourceUrl": "https://t.me/addstickers/vibe_flag",
  "width": 192,
  "height": 192,
  "kind": "animated",
  "mediaType": "video/webm",
  "sourceFormat": "video",
  "assetPath": "vibe-flag/017.270ec8f6b61d.webm",
  "src": "/stickers/vibe-flag/017.270ec8f6b61d.webm",
  "fps": 24,
  "frameCount": 71,
  "duration": 2.959,
  "sha256": "270ec8f6b61da4bc26bf42ea42fa4e9b67392c4719f575e34af72c6620273406",
  "firstFrameAssetPath": "vibe-flag/017.first-frame.010ccd9a2d59.webp",
  "firstFrameSrc": "/stickers/vibe-flag/017.first-frame.010ccd9a2d59.webp"
}
